lmtr_agents/__init__.py
lmtr_agents/__main__.py
lmtr_agents/lmtr_agents.py
lmtr_agents/templates.py
lmtr_agents-0.1.0a2.dist-info/METADATA
lmtr_agents-0.1.0a2.dist-info/WHEEL
lmtr_agents-0.1.0a2.dist-info/entry_points.txt
lmtr_agents-0.1.0a2.dist-info/licenses/LICENSE
lmtr_agents-0.1.0a2.dist-info/RECORD
