Metadata-Version: 2.3
Name: lmtr-agents
Version: 0.1.0a2
Summary: Various llm agents (agent_chat, agent_tr, agent_ref, agent_imp, agent_comb) for translation
Author: ffreemt
License-Expression: MIT
License-File: LICENSE
Requires-Python: >=3.8
Requires-Dist: langchain-openai>=0.1.17
Requires-Dist: langchain>=0.2.10
Requires-Dist: loguru>=0.7.2
Requires-Dist: python-dotenv>=1.0.1
Requires-Dist: rich>=13.7.1
Requires-Dist: typer>=0.12.1
Requires-Dist: ycecream>=1.3.17
